{
  "version": "7",
  "dialect": "postgresql",
  "entries": [
    {
      "idx": 0,
      "version": "7",
      "when": 1736203236401,
      "tag": "0000_mighty_gravity",
      "breakpoints": true
    },
    {
      "idx": 1,
      "version": "7",
      "when": 1736265909633,
      "tag": "0001_funny_sally_floyd",
      "breakpoints": true
    },
    {
      "idx": 2,
      "version": "7",
      "when": 1736286216418,
      "tag": "0002_wakeful_nocturne",
      "breakpoints": true
    },
    {
      "idx": 3,
      "version": "7",
      "when": 1736344773545,
      "tag": "0003_aberrant_emma_frost",
      "breakpoints": true
    }
  ]
}